zvolv_sdk/__init__.py
zvolv_sdk/client.py
zvolv_sdk/server_configuration.py
zvolv_sdk/test/__init__.py
zvolv_sdk/test/test_client.py
zvolv_sdk/test/test_client_one.py
zvolvAuth-0.0.15.dist-info/LICENSE
zvolvAuth-0.0.15.dist-info/METADATA
zvolvAuth-0.0.15.dist-info/WHEEL
zvolvAuth-0.0.15.dist-info/top_level.txt
zvolvAuth-0.0.15.dist-info/RECORD
